dafsa/__init__.py
dafsa/__main__.py
dafsa/dafsa.py
dafsa/output.py
dafsa/utils.py
resources/ciura.txt
resources/dna.txt
resources/phonemes.txt
resources/template.dot
resources/tresoldi.txt
dafsa-1.0.dist-info/AUTHORS.md
dafsa-1.0.dist-info/LICENSE
dafsa-1.0.dist-info/METADATA
dafsa-1.0.dist-info/WHEEL
dafsa-1.0.dist-info/entry_points.txt
dafsa-1.0.dist-info/top_level.txt
dafsa-1.0.dist-info/RECORD
