Metadata-Version: 2.1
Name: dafsa
Version: 1.0
Summary: Library for computing Deterministic Acyclic Finite State Automata (DAFSA)
Home-page: https://github.com/tresoldi/dafsa
Author: Tiago Tresoldi
Author-email: tresoldi@shh.mpg.de
License: MIT
Project-URL: Documentation, https://dafsa.readthedocs.io
Keywords: dafsa,dawg,finite state automata,deterministic acyclic finite state automaton,directed acyclic word graph
Platform: UNKNOWN
Classifier: License :: OSI Approved :: MIT License
Classifier: Programming Language :: Python :: 3
Classifier: Operating System :: OS Independent
Classifier: Topic :: Software Development :: Libraries
Requires-Dist: networkx
